earthcare_downloader/__init__.py
earthcare_downloader/aio.py
earthcare_downloader/api.py
earthcare_downloader/cli.py
earthcare_downloader/dl.py
earthcare_downloader/html_parser.py
earthcare_downloader/metadata.py
earthcare_downloader/params.py
earthcare_downloader/products.py
earthcare_downloader/py.typed
earthcare_downloader/utils.py
earthcare_downloader/version.py
earthcare_downloader-1.8.6.dist-info/METADATA
earthcare_downloader-1.8.6.dist-info/WHEEL
earthcare_downloader-1.8.6.dist-info/entry_points.txt
earthcare_downloader-1.8.6.dist-info/licenses/LICENSE
earthcare_downloader-1.8.6.dist-info/RECORD
