Metadata-Version: 2.4
Name: earthcare-downloader
Version: 1.8.6
Summary: Download EarthCARE satellite data
Project-URL: Homepage, https://github.com/actris-cloudnet/earthcare-downloader
Project-URL: Issues, https://github.com/actris-cloudnet/earthcare-downloader/issues
Author-email: Simo Tukiainen <simo.tukiainen@fmi.fi>
License-File: LICENSE
Classifier: Development Status :: 4 - Beta
Classifier: Intended Audience :: Science/Research
Classifier: License :: OSI Approved :: MIT License
Classifier: Operating System :: OS Independent
Classifier: Programming Language :: Python :: 3
Classifier: Topic :: Scientific/Engineering :: Atmospheric Science
Requires-Python: >=3.10
Requires-Dist: aiohttp
Requires-Dist: beautifulsoup4
Requires-Dist: platformdirs
Requires-Dist: tqdm
Provides-Extra: dev
Requires-Dist: mypy; extra == 'dev'
Requires-Dist: pre-commit; extra == 'dev'
Requires-Dist: release-version; extra == 'dev'
Requires-Dist: types-tqdm; extra == 'dev'
Provides-Extra: test
Requires-Dist: pytest; extra == 'test'
